grn_analysis_tools/__init__.py
grn_analysis_tools/helper_functions.py
grn_analysis_tools-0.0.1.dist-info/METADATA
grn_analysis_tools-0.0.1.dist-info/WHEEL
grn_analysis_tools-0.0.1.dist-info/licenses/LICENSE
grn_analysis_tools-0.0.1.dist-info/RECORD
